latextomd/__init__.py
latextomd/__main__.py
latextomd/cli.py
latextomd/config.py
latextomd/latexblocks.py
latextomd/latextomd.py
latextomd/postpandoc.py
latextomd/prepandoc.py
latextomd/soup.py
latextomd/text_manipulation.py
latextomd-0.1.6.dist-info/entry_points.txt
latextomd-0.1.6.dist-info/LICENSE
latextomd-0.1.6.dist-info/WHEEL
latextomd-0.1.6.dist-info/METADATA
latextomd-0.1.6.dist-info/RECORD
